pandasvalidation.py
pandas_validation-0.5.0.dist-info/LICENSE.txt
pandas_validation-0.5.0.dist-info/METADATA
pandas_validation-0.5.0.dist-info/WHEEL
pandas_validation-0.5.0.dist-info/top_level.txt
pandas_validation-0.5.0.dist-info/RECORD
