Metadata-Version: 2.1
Name: pandas-validation
Version: 0.5.0
Summary: A Python package for validating data with pandas
Home-page: https://github.com/jmenglund/pandas-validation
Author: Markus Englund
Author-email: jan.markus.englund@gmail.com
License: MIT
Keywords: pandas,validation
Platform: UNKNOWN
Classifier: Development Status :: 5 - Production/Stable
Classifier: Intended Audience :: Developers
Classifier: License :: OSI Approved :: MIT License
Classifier: Operating System :: OS Independent
Classifier: Programming Language :: Python
Classifier: Programming Language :: Python :: 3
Classifier: Programming Language :: Python :: 3.5
Classifier: Programming Language :: Python :: 3.6
Requires-Dist: pandas (>=0.22)
